monitored_ioloop/__init__.py
monitored_ioloop/exceptions.py
monitored_ioloop/monioted_ioloop_base.py
monitored_ioloop/monitored_asyncio_ioloop.py
monitored_ioloop/monitored_uvloop_ioloop.py
monitored_ioloop/monitoring.py
monitored_ioloop/types.py
monitored_ioloop-0.1.7.dist-info/LICENSE
monitored_ioloop-0.1.7.dist-info/METADATA
monitored_ioloop-0.1.7.dist-info/WHEEL
monitored_ioloop-0.1.7.dist-info/RECORD
