Metadata-Version: 2.1
Name: monitored_ioloop
Version: 0.1.7
Summary: 
Author: gnir
Author-email: gnir.work@gmail.com
Requires-Python: >=3.10,<4.0
Classifier: Programming Language :: Python :: 3
Classifier: Programming Language :: Python :: 3.10
Classifier: Programming Language :: Python :: 3.11
Classifier: Programming Language :: Python :: 3.12
